google/cloud/memcache/__init__.py
google/cloud/memcache/gapic_version.py
google/cloud/memcache/py.typed
google/cloud/memcache_v1/__init__.py
google/cloud/memcache_v1/gapic_metadata.json
google/cloud/memcache_v1/gapic_version.py
google/cloud/memcache_v1/py.typed
google/cloud/memcache_v1/services/__init__.py
google/cloud/memcache_v1/services/cloud_memcache/__init__.py
google/cloud/memcache_v1/services/cloud_memcache/async_client.py
google/cloud/memcache_v1/services/cloud_memcache/client.py
google/cloud/memcache_v1/services/cloud_memcache/pagers.py
google/cloud/memcache_v1/services/cloud_memcache/transports/__init__.py
google/cloud/memcache_v1/services/cloud_memcache/transports/base.py
google/cloud/memcache_v1/services/cloud_memcache/transports/grpc.py
google/cloud/memcache_v1/services/cloud_memcache/transports/grpc_asyncio.py
google/cloud/memcache_v1/services/cloud_memcache/transports/rest.py
google/cloud/memcache_v1/services/cloud_memcache/transports/rest_base.py
google/cloud/memcache_v1/types/__init__.py
google/cloud/memcache_v1/types/cloud_memcache.py
google/cloud/memcache_v1beta2/__init__.py
google/cloud/memcache_v1beta2/gapic_metadata.json
google/cloud/memcache_v1beta2/gapic_version.py
google/cloud/memcache_v1beta2/py.typed
google/cloud/memcache_v1beta2/services/__init__.py
google/cloud/memcache_v1beta2/services/cloud_memcache/__init__.py
google/cloud/memcache_v1beta2/services/cloud_memcache/async_client.py
google/cloud/memcache_v1beta2/services/cloud_memcache/client.py
google/cloud/memcache_v1beta2/services/cloud_memcache/pagers.py
google/cloud/memcache_v1beta2/services/cloud_memcache/transports/__init__.py
google/cloud/memcache_v1beta2/services/cloud_memcache/transports/base.py
google/cloud/memcache_v1beta2/services/cloud_memcache/transports/grpc.py
google/cloud/memcache_v1beta2/services/cloud_memcache/transports/grpc_asyncio.py
google/cloud/memcache_v1beta2/services/cloud_memcache/transports/rest.py
google_cloud_memcache-1.12.1.dist-info/LICENSE
google_cloud_memcache-1.12.1.dist-info/METADATA
google_cloud_memcache-1.12.1.dist-info/WHEEL
google_cloud_memcache-1.12.1.dist-info/top_level.txt
google_cloud_memcache-1.12.1.dist-info/RECORD
